dapr_api_wrapper/__init__.py
dapr_api_wrapper/requests/__init__.py
dapr_api_wrapper/requests/api.py
dapr_api_wrapper/requests/exceptions.py
dapr_api_wrapper/requests/request.py
dapr_api_wrapper/samples/__init__.py
dapr_api_wrapper/samples/binder.py
dapr_api_wrapper/samples/demo_actor.py
dapr_api_wrapper/samples/demo_actor_interface.py
dapr_api_wrapper/samples/listen.py
dapr_api_wrapper/samples/subscribe.py
dapr_api_wrapper/setup/__init__.py
dapr_api_wrapper-1.2.8.dist-info/LICENSE
dapr_api_wrapper-1.2.8.dist-info/METADATA
dapr_api_wrapper-1.2.8.dist-info/WHEEL
dapr_api_wrapper-1.2.8.dist-info/top_level.txt
dapr_api_wrapper-1.2.8.dist-info/RECORD
