Metadata-Version: 2.1
Name: dapr-api-wrapper
Version: 1.2.8
Summary: Requests-like Interface to easily switch to dapr APIs from requests library
Home-page: https://github.com/Microland/Dapr-API-Wrapper
Author: Avijeet Diwaker
License: UNKNOWN
Project-URL: Bug Tracker, https://github.com/Microland/Dapr-API-Wrapper/issues
Platform: UNKNOWN
Classifier: Programming Language :: Python :: 3
Classifier: License :: OSI Approved :: MIT License
Classifier: Operating System :: OS Independent
Requires-Python: >=3.8
License-File: LICENSE
Requires-Dist: dapr (>=1.1.0)
Requires-Dist: dapr-ext-grpc (>=1.1.0)
